ehelply_cacher/Cache.py
ehelply_cacher/__init__.py
tests/__init__.py
tests/test_cacher.py
ehelply_cacher-0.1.0.dist-info/LICENSE
ehelply_cacher-0.1.0.dist-info/METADATA
ehelply_cacher-0.1.0.dist-info/WHEEL
ehelply_cacher-0.1.0.dist-info/top_level.txt
ehelply_cacher-0.1.0.dist-info/RECORD
