Metadata-Version: 2.1
Name: ehelply-cacher
Version: 0.1.0
Summary: eHelply Cacher
Home-page: https://github.com/ehelply/Cacher
Author: Shawn Clake
Author-email: shawn.clake@gmail.com
License: UNKNOWN
Platform: UNKNOWN
Classifier: Programming Language :: Python :: 3
Classifier: License :: OSI Approved :: GNU General Public License v3 (GPLv3)
Classifier: Operating System :: OS Independent
Requires-Dist: pytest
Requires-Dist: cachetools (==3.1.1)
